swimlane_connector_exceptions/__init__.py
swimlane_connector_exceptions/exceptions.py
swimlane_connector_exceptions-1.0.1.dist-info/LICENSE
swimlane_connector_exceptions-1.0.1.dist-info/METADATA
swimlane_connector_exceptions-1.0.1.dist-info/WHEEL
swimlane_connector_exceptions-1.0.1.dist-info/top_level.txt
swimlane_connector_exceptions-1.0.1.dist-info/RECORD
